pravah_scrapper.py
pravah_scrapper-0.0.5.dist-info/METADATA
pravah_scrapper-0.0.5.dist-info/WHEEL
pravah_scrapper-0.0.5.dist-info/top_level.txt
pravah_scrapper-0.0.5.dist-info/RECORD
