Metadata-Version: 2.1
Name: pravah-scrapper
Version: 0.0.5
Summary: Scrapping framework
Home-page: https://github.com/upperwal
Author: Abhishek Upperwal
Author-email: mesh@soket.in
License: UNKNOWN
Platform: UNKNOWN
Classifier: Programming Language :: Python :: 3
Classifier: License :: OSI Approved :: MIT License
Classifier: Operating System :: OS Independent
Requires-Dist: dytimer
